pyphe/__init__.py
pyphe/analysis.py
pyphe/growthcurves.py
pyphe/interpret.py
pyphe/quantify.py
pyphe/scan.py
pyphe-0.983.data/scripts/pyphe-analyse
pyphe-0.983.data/scripts/pyphe-analyse-gui
pyphe-0.983.data/scripts/pyphe-analyse.bat
pyphe-0.983.data/scripts/pyphe-growthcurves
pyphe-0.983.data/scripts/pyphe-growthcurves.bat
pyphe-0.983.data/scripts/pyphe-interpret
pyphe-0.983.data/scripts/pyphe-interpret.bat
pyphe-0.983.data/scripts/pyphe-quantify
pyphe-0.983.data/scripts/pyphe-quantify.bat
pyphe-0.983.data/scripts/pyphe-scan
pyphe-0.983.data/scripts/pyphe-scan-timecourse
pyphe-0.983.dist-info/LICENSE
pyphe-0.983.dist-info/METADATA
pyphe-0.983.dist-info/WHEEL
pyphe-0.983.dist-info/top_level.txt
pyphe-0.983.dist-info/RECORD
