Metadata-Version: 2.1
Name: pyphe
Version: 0.983
Summary: Python toolbox for phenotype analysis of arrayed microbial colonies
Home-page: https://github.com/Bahler-Lab/pyphe
Author: Stephan Kamrad
Author-email: stephan.kamrad@gmail.com
License: MIT
Classifier: Development Status :: 4 - Beta
Classifier: Programming Language :: Python :: 3
Classifier: License :: OSI Approved :: MIT License
Classifier: Operating System :: OS Independent
Requires-Python: >=3.7
License-File: LICENSE
Requires-Dist: pandas
Requires-Dist: matplotlib
Requires-Dist: numpy
Requires-Dist: seaborn
Requires-Dist: scipy
Requires-Dist: scikit-image
Requires-Dist: scikit-learn
